MilestoneMap/__init__.py
MilestoneMap/core.py
MilestoneMap/log.py
MilestoneMap/server.py
milestonemap-0.1.1.dist-info/METADATA
milestonemap-0.1.1.dist-info/WHEEL
milestonemap-0.1.1.dist-info/top_level.txt
milestonemap-0.1.1.dist-info/RECORD
